asgi_matomo/__init__.py
asgi_matomo/middleware.py
asgi_matomo/py.typed
asgi_matomo/trackers.py
asgi_matomo-0.6.0.dist-info/METADATA
asgi_matomo-0.6.0.dist-info/WHEEL
asgi_matomo-0.6.0.dist-info/licenses/LICENSE
asgi_matomo-0.6.0.dist-info/RECORD
