Metadata-Version: 2.1
Name: asgi-matomo
Version: 0.6.0
Summary: Middleware for tracking ASGI requests with Matomo
Project-URL: homepage, https://spraakbanken.gu.se
Project-URL: repository, https://github.com/spraakbanken/asgi-matomo
Project-URL: Bug Tracker, https://github.com/spraakbanken/asgi-matomo/issues
Author-email: Kristoffer Andersson <kristoffer.andersson@gu.se>
License-Expression: MIT
License-File: LICENSE
Requires-Python: >=3.10
Requires-Dist: asgiref>=3.6.0
Requires-Dist: httpx>=0.24
Provides-Extra: ci
Requires-Dist: ruff>=0.1.4; extra == 'ci'
Provides-Extra: docs
Requires-Dist: markdown>=3.5.1; extra == 'docs'
Requires-Dist: mdx-include>=1.4.2; extra == 'docs'
Requires-Dist: mike>=2.0.0; extra == 'docs'
Requires-Dist: mkdocs-markdownextradata-plugin>=0.2.5; extra == 'docs'
Requires-Dist: mkdocs-material>=9.4.8; extra == 'docs'
Requires-Dist: mkdocs>=1.5.3; extra == 'docs'
